yams/__main__.py
yams/bluetooth_device.py
yams/bt_scanner.py
yams/config.py
yams/data_explorer.py
yams/data_extraction.py
yams/e_stop.py
yams/file_extractor.py
yams/msense_collector.py
yams/uuid_extractor.py
yams_util-1.3.0.dist-info/licenses/LICENSE
yams_util-1.3.0.dist-info/METADATA
yams_util-1.3.0.dist-info/WHEEL
yams_util-1.3.0.dist-info/top_level.txt
yams_util-1.3.0.dist-info/RECORD
