Metadata-Version: 2.4
Name: yams-util
Version: 1.3.0
Summary: Yet Another MotionSenSE Service Utility
Author-email: Yuyi Chang <roomier_guanine_05@icloud.com>
Project-URL: Homepage, https://github.com/SenSE-Lab-OSU/YAMS
Project-URL: Issues, https://github.com/SenSE-Lab-OSU/YAMS/issues
Classifier: Programming Language :: Python :: 3
Classifier: Operating System :: OS Independent
Requires-Python: >=3.12
License-File: LICENSE
Requires-Dist: bleak
Requires-Dist: gradio
Requires-Dist: psutil
Requires-Dist: apscheduler
Requires-Dist: matplotlib
Requires-Dist: simplepyble
Requires-Dist: pylsl
Dynamic: license-file
